{"py/object": "rasa_core.featurizers.MaxHistoryTrackerFeaturizer", "max_history": 5, "remove_duplicates": true, "state_featurizer": {"py/object": "rasa_core.featurizers.BinarySingleStateFeaturizer", "input_state_map": {"entity_keywords": 10, "entity_product": 8, "entity_version": 9, "intent_affirm": 1, "intent_deny": 2, "intent_goodbye": 7, "intent_greet": 0, "intent_inform": 6, "intent_question": 3, "intent_request_info": 5, "intent_thanks": 4, "prev_action_listen": 14, "prev_action_restart": 15, "prev_action_search": 29, "prev_action_suggest": 30, "prev_utter_ack_dosearch": 20, "prev_utter_ack_findalternatives": 21, "prev_utter_anything_else": 27, "prev_utter_ask_details": 25, "prev_utter_ask_didthathelp": 28, "prev_utter_ask_howcanhelp": 23, "prev_utter_ask_product": 22, "prev_utter_ask_version": 24, "prev_utter_default": 19, "prev_utter_goodbye": 17, "prev_utter_greet": 16, "prev_utter_on_it": 26, "prev_utter_structured_garbage": 32, "prev_utter_thanks": 18, "prev_utter_unstructured_garbage": 31, "slot_keywords_0": 11, "slot_product_0": 12, "slot_version_0": 13}, "num_features": 33, "slot_feature_len": 3, "user_feature_len": 11}, "use_intent_probabilities": false}